git_cleaner/__init__.py
git_cleaner/__main__.py
git_cleaner/__version__.py
git_cleaner/branches.py
git_cleaner/cli.py
git_cleaner/config.py
git_cleaner/filters.py
git_cleaner/formats.py
git_cleaner/git.py
git_cleaner/notifications.py
git_cleaner/oauth.py
git_cleaner-0.3.4.dist-info/METADATA
git_cleaner-0.3.4.dist-info/RECORD
git_cleaner-0.3.4.dist-info/WHEEL
git_cleaner-0.3.4.dist-info/entry_points.txt
git_cleaner-0.3.4.dist-info/top_level.txt
