Metadata-Version: 2.1
Name: git-cleaner
Version: 0.3.4
Summary: Cleanup merged branches with notification to last committer.
Home-page: https://github.com/d-k-ivanov/py-git-cleaner
Author: Dmitriy Ivanov
Author-email: d.k.ivanov@live.com
License: UNKNOWN
Platform: UNKNOWN
Classifier: Environment :: Console
Classifier: License :: OSI Approved :: MIT License
Classifier: Intended Audience :: Developers
Classifier: Intended Audience :: System Administrators
Classifier: Programming Language :: Python
Classifier: Programming Language :: Python :: 3
Classifier: Programming Language :: Python :: 3.5
Classifier: Programming Language :: Python :: 3.6
Classifier: Programming Language :: Python :: 3.7
Classifier: Programming Language :: Python :: Implementation :: CPython
Classifier: Topic :: Software Development :: Version Control :: Git
Requires-Python: >=3.6.0
Requires-Dist: click
Requires-Dist: markdown
Requires-Dist: oauthlib
Requires-Dist: python-dotenv
Requires-Dist: pytz
Requires-Dist: requests
Requires-Dist: requests-oauthlib
Requires-Dist: urllib3
